{
  "type": "minecraft:crafting_shapeless",
  "ingredients": [
    {
      "item": "endium:endium_scrap"
    },
    {
      "item": "endium:endium_scrap"
    },
    {
      "item": "endium:endium_scrap"
    },
    {
      "item": "endium:endium_scrap"
    },
    {
      "item": "minecraft:echo_shard"
    },
    {
      "item": "minecraft:echo_shard"
    },
    {
      "item": "minecraft:echo_shard"
    },
    {
      "item": "minecraft:echo_shard"
    }
  ],
  "result": {
    "item": "endium:endium_ingot"
  }
}